{
    "version": "5.2.1",
    "flags": {},
    "shapes": [
        {
            "label": "sitting",
            "points": [
                [
                    385.0,
                    179.0
                ],
                [
                    448.0,
                    240.0
                ]
            ],
            "group_id": null,
            "description": "",
            "shape_type": "rectangle",
            "flags": {}
        },
        {
            "label": "standing",
            "points": [
                [
                    188.0,
                    132.0
                ],
                [
                    243.0,
                    212.0
                ]
            ],
            "group_id": null,
            "description": "",
            "shape_type": "rectangle",
            "flags": {}
        },
        {
            "label": "standing",
            "points": [
                [
                    54.0,
                    181.0
                ],
                [
                    109.0,
                    309.0
                ]
            ],
            "group_id": null,
            "description": "",
            "shape_type": "rectangle",
            "flags": {}
        },
        {
            "label": "standing",
            "points": [
                [
                    336.0,
                    126.0
                ],
                [
                    366.0,
                    217.0
                ]
            ],
            "group_id": null,
            "description": "",
            "shape_type": "rectangle",
            "flags": {}
        },
        {
            "label": "standing",
            "points": [
                [
                    45.0,
                    161.0
                ],
                [
                    68.0,
                    248.0
                ]
            ],
            "group_id": null,
            "description": "",
            "shape_type": "rectangle",
            "flags": {}
        }
    ],
    "imagePath": "000116.png",
    "imageData": null,
    "imageHeight": 345,
    "imageWidth": 640
}