{
    "version": "5.2.1",
    "flags": {},
    "shapes": [
        {
            "label": "standing",
            "points": [
                [
                    56.0,
                    69.0
                ],
                [
                    91.0,
                    136.0
                ]
            ],
            "group_id": null,
            "description": "",
            "shape_type": "rectangle",
            "flags": {}
        },
        {
            "label": "standing",
            "points": [
                [
                    188.0,
                    165.0
                ],
                [
                    252.0,
                    255.0
                ]
            ],
            "group_id": null,
            "description": "",
            "shape_type": "rectangle",
            "flags": {}
        },
        {
            "label": "standing",
            "points": [
                [
                    244.0,
                    48.0
                ],
                [
                    274.0,
                    111.0
                ]
            ],
            "group_id": null,
            "description": "",
            "shape_type": "rectangle",
            "flags": {}
        },
        {
            "label": "standing",
            "points": [
                [
                    474.0,
                    91.0
                ],
                [
                    507.0,
                    166.0
                ]
            ],
            "group_id": null,
            "description": "",
            "shape_type": "rectangle",
            "flags": {}
        },
        {
            "label": "sitting",
            "points": [
                [
                    497.0,
                    61.0
                ],
                [
                    521.0,
                    92.0
                ]
            ],
            "group_id": null,
            "description": "",
            "shape_type": "rectangle",
            "flags": {}
        }
    ],
    "imagePath": "000306.png",
    "imageData": null,
    "imageHeight": 345,
    "imageWidth": 640
}