{
    "version": "5.2.1",
    "flags": {},
    "shapes": [
        {
            "label": "standing",
            "points": [
                [
                    409.0,
                    203.0
                ],
                [
                    460.0,
                    299.0
                ]
            ],
            "group_id": null,
            "description": "",
            "shape_type": "rectangle",
            "flags": {}
        },
        {
            "label": "throwing",
            "points": [
                [
                    54.0,
                    194.0
                ],
                [
                    144.0,
                    292.0
                ]
            ],
            "group_id": null,
            "description": "",
            "shape_type": "rectangle",
            "flags": {}
        },
        {
            "label": "standing",
            "points": [
                [
                    422.0,
                    140.0
                ],
                [
                    451.0,
                    210.0
                ]
            ],
            "group_id": null,
            "description": "",
            "shape_type": "rectangle",
            "flags": {}
        },
        {
            "label": "standing",
            "points": [
                [
                    313.0,
                    98.0
                ],
                [
                    336.0,
                    165.0
                ]
            ],
            "group_id": null,
            "description": "",
            "shape_type": "rectangle",
            "flags": {}
        }
    ],
    "imagePath": "000550.png",
    "imageData": null,
    "imageHeight": 345,
    "imageWidth": 640
}