{
    "version": "5.2.1",
    "flags": {},
    "shapes": [
        {
            "label": "standing",
            "points": [
                [
                    90.0,
                    69.0
                ],
                [
                    124.0,
                    133.0
                ]
            ],
            "group_id": null,
            "description": "",
            "shape_type": "rectangle",
            "flags": {}
        },
        {
            "label": "standing",
            "points": [
                [
                    65.0,
                    117.0
                ],
                [
                    95.0,
                    196.0
                ]
            ],
            "group_id": null,
            "description": "",
            "shape_type": "rectangle",
            "flags": {}
        },
        {
            "label": "standing",
            "points": [
                [
                    53.0,
                    191.0
                ],
                [
                    99.0,
                    292.0
                ]
            ],
            "group_id": null,
            "description": "",
            "shape_type": "rectangle",
            "flags": {}
        },
        {
            "label": "throwing",
            "points": [
                [
                    376.0,
                    204.0
                ],
                [
                    445.0,
                    290.0
                ]
            ],
            "group_id": null,
            "description": "",
            "shape_type": "rectangle",
            "flags": {}
        },
        {
            "label": "standing",
            "points": [
                [
                    290.0,
                    57.0
                ],
                [
                    312.0,
                    108.0
                ]
            ],
            "group_id": null,
            "description": "",
            "shape_type": "rectangle",
            "flags": {}
        },
        {
            "label": "standing",
            "points": [
                [
                    392.0,
                    147.0
                ],
                [
                    416.0,
                    211.0
                ]
            ],
            "group_id": null,
            "description": "",
            "shape_type": "rectangle",
            "flags": {}
        }
    ],
    "imagePath": "000662.png",
    "imageData": null,
    "imageHeight": 345,
    "imageWidth": 640
}