{
    "version": "5.2.1",
    "flags": {},
    "shapes": [
        {
            "label": "standing",
            "points": [
                [
                    8.0,
                    196.0
                ],
                [
                    69.0,
                    314.0
                ]
            ],
            "group_id": null,
            "description": "",
            "shape_type": "rectangle",
            "flags": {}
        },
        {
            "label": "throwing",
            "points": [
                [
                    385.0,
                    216.0
                ],
                [
                    438.0,
                    311.0
                ]
            ],
            "group_id": null,
            "description": "",
            "shape_type": "rectangle",
            "flags": {}
        },
        {
            "label": "standing",
            "points": [
                [
                    382.0,
                    144.0
                ],
                [
                    413.0,
                    218.0
                ]
            ],
            "group_id": null,
            "description": "",
            "shape_type": "rectangle",
            "flags": {}
        },
        {
            "label": "standing",
            "points": [
                [
                    343.0,
                    82.0
                ],
                [
                    370.0,
                    155.0
                ]
            ],
            "group_id": null,
            "description": "",
            "shape_type": "rectangle",
            "flags": {}
        },
        {
            "label": "standing",
            "points": [
                [
                    94.0,
                    74.0
                ],
                [
                    117.0,
                    143.0
                ]
            ],
            "group_id": null,
            "description": "",
            "shape_type": "rectangle",
            "flags": {}
        },
        {
            "label": "standing",
            "points": [
                [
                    66.0,
                    103.0
                ],
                [
                    102.0,
                    168.0
                ]
            ],
            "group_id": null,
            "description": "",
            "shape_type": "rectangle",
            "flags": {}
        }
    ],
    "imagePath": "000965.png",
    "imageData": null,
    "imageHeight": 345,
    "imageWidth": 640
}