{
    "version": "5.2.1",
    "flags": {},
    "shapes": [
        {
            "label": "lying",
            "points": [
                [
                    122.0,
                    180.0
                ],
                [
                    203.0,
                    247.0
                ]
            ],
            "group_id": null,
            "description": "",
            "shape_type": "rectangle",
            "flags": {}
        }
    ],
    "imagePath": "001275.png",
    "imageData": null,
    "imageHeight": 345,
    "imageWidth": 640
}