{
    "version": "5.2.1",
    "flags": {},
    "shapes": [
        {
            "label": "sitting",
            "points": [
                [
                    357.0,
                    216.0
                ],
                [
                    381.0,
                    243.0
                ]
            ],
            "group_id": null,
            "description": "",
            "shape_type": "rectangle",
            "flags": {}
        },
        {
            "label": "sitting",
            "points": [
                [
                    303.0,
                    181.0
                ],
                [
                    333.0,
                    223.0
                ]
            ],
            "group_id": null,
            "description": "",
            "shape_type": "rectangle",
            "flags": {}
        },
        {
            "label": "sitting",
            "points": [
                [
                    411.0,
                    120.0
                ],
                [
                    437.0,
                    155.0
                ]
            ],
            "group_id": null,
            "description": "",
            "shape_type": "rectangle",
            "flags": {}
        },
        {
            "label": "sitting",
            "points": [
                [
                    169.0,
                    112.0
                ],
                [
                    189.0,
                    151.0
                ]
            ],
            "group_id": null,
            "description": "",
            "shape_type": "rectangle",
            "flags": {}
        },
        {
            "label": "standing",
            "points": [
                [
                    311.0,
                    79.0
                ],
                [
                    332.0,
                    133.0
                ]
            ],
            "group_id": null,
            "description": "",
            "shape_type": "rectangle",
            "flags": {}
        }
    ],
    "imagePath": "001654.png",
    "imageData": null,
    "imageHeight": 345,
    "imageWidth": 640
}