{
    "version": "5.2.1",
    "flags": {},
    "shapes": [
        {
            "label": "standing",
            "points": [
                [
                    453.0,
                    137.0
                ],
                [
                    491.0,
                    219.0
                ]
            ],
            "group_id": null,
            "description": "",
            "shape_type": "rectangle",
            "flags": {}
        },
        {
            "label": "lying",
            "points": [
                [
                    174.0,
                    102.0
                ],
                [
                    244.0,
                    145.0
                ]
            ],
            "group_id": null,
            "description": "",
            "shape_type": "rectangle",
            "flags": {}
        },
        {
            "label": "standing",
            "points": [
                [
                    282.0,
                    57.0
                ],
                [
                    302.0,
                    131.0
                ]
            ],
            "group_id": null,
            "description": "",
            "shape_type": "rectangle",
            "flags": {}
        },
        {
            "label": "standing",
            "points": [
                [
                    70.0,
                    195.0
                ],
                [
                    135.0,
                    300.0
                ]
            ],
            "group_id": null,
            "description": "",
            "shape_type": "rectangle",
            "flags": {}
        },
        {
            "label": "lying",
            "points": [
                [
                    66.0,
                    163.0
                ],
                [
                    178.0,
                    200.0
                ]
            ],
            "group_id": null,
            "description": "",
            "shape_type": "rectangle",
            "flags": {}
        },
        {
            "label": "lying",
            "points": [
                [
                    132.0,
                    165.0
                ],
                [
                    178.0,
                    196.0
                ]
            ],
            "group_id": null,
            "description": "",
            "shape_type": "rectangle",
            "flags": {}
        }
    ],
    "imagePath": "001823.png",
    "imageData": null,
    "imageHeight": 345,
    "imageWidth": 640
}