{
    "version": "5.2.1",
    "flags": {},
    "shapes": [
        {
            "label": "sitting",
            "points": [
                [
                    170.0,
                    122.0
                ],
                [
                    300.0,
                    333.0
                ]
            ],
            "group_id": null,
            "description": "",
            "shape_type": "rectangle",
            "flags": {}
        },
        {
            "label": "standing",
            "points": [
                [
                    16.0,
                    116.0
                ],
                [
                    161.0,
                    342.0
                ]
            ],
            "group_id": null,
            "description": "",
            "shape_type": "rectangle",
            "flags": {}
        }
    ],
    "imagePath": "001997.png",
    "imageData": null,
    "imageHeight": 345,
    "imageWidth": 640
}