{
    "version": "5.2.1",
    "flags": {},
    "shapes": [
        {
            "label": "standing",
            "points": [
                [
                    1.0,
                    157.0
                ],
                [
                    103.0,
                    341.0
                ]
            ],
            "group_id": null,
            "description": "",
            "shape_type": "rectangle",
            "flags": {}
        },
        {
            "label": "standing",
            "points": [
                [
                    90.0,
                    16.0
                ],
                [
                    185.0,
                    279.0
                ]
            ],
            "group_id": null,
            "description": "",
            "shape_type": "rectangle",
            "flags": {}
        },
        {
            "label": "sitting",
            "points": [
                [
                    155.0,
                    128.0
                ],
                [
                    275.0,
                    337.0
                ]
            ],
            "group_id": null,
            "description": "",
            "shape_type": "rectangle",
            "flags": {}
        }
    ],
    "imagePath": "002064.png",
    "imageData": null,
    "imageHeight": 345,
    "imageWidth": 640
}